odoo10_addon_website_snippet_country_dropdown-10.0.1.0.0-py2.7-nspkg.pth
odoo/addons/website_snippet_country_dropdown/README.rst
odoo/addons/website_snippet_country_dropdown/__init__.py
odoo/addons/website_snippet_country_dropdown/__manifest__.py
odoo/addons/website_snippet_country_dropdown/demo/assets.xml
odoo/addons/website_snippet_country_dropdown/demo/pages.xml
odoo/addons/website_snippet_country_dropdown/i18n/en.po
odoo/addons/website_snippet_country_dropdown/i18n/es.po
odoo/addons/website_snippet_country_dropdown/i18n/fr.po
odoo/addons/website_snippet_country_dropdown/i18n/sl.po
odoo/addons/website_snippet_country_dropdown/static/description/icon.png
odoo/addons/website_snippet_country_dropdown/static/src/css/style.sass
odoo/addons/website_snippet_country_dropdown/static/src/js/web_tour_country_dropdown.js
odoo/addons/website_snippet_country_dropdown/static/src/js/website_snippet_country_dropdown.js
odoo/addons/website_snippet_country_dropdown/static/src/xml/country_dropdown.xml
odoo/addons/website_snippet_country_dropdown/tests/__init__.py
odoo/addons/website_snippet_country_dropdown/tests/test_snippet_country_dropdown.py
odoo/addons/website_snippet_country_dropdown/views/assets.xml
odoo/addons/website_snippet_country_dropdown/views/snippets.xml
odoo10_addon_website_snippet_country_dropdown-10.0.1.0.0.dist-info/DESCRIPTION.rst
odoo10_addon_website_snippet_country_dropdown-10.0.1.0.0.dist-info/METADATA
odoo10_addon_website_snippet_country_dropdown-10.0.1.0.0.dist-info/RECORD
odoo10_addon_website_snippet_country_dropdown-10.0.1.0.0.dist-info/WHEEL
odoo10_addon_website_snippet_country_dropdown-10.0.1.0.0.dist-info/metadata.json
odoo10_addon_website_snippet_country_dropdown-10.0.1.0.0.dist-info/namespace_packages.txt
odoo10_addon_website_snippet_country_dropdown-10.0.1.0.0.dist-info/top_level.txt
